pphp.py
pphp-3.3.1.dist-info/WHEEL
pphp-3.3.1.dist-info/metadata.json
pphp-3.3.1.dist-info/top_level.txt
pphp-3.3.1.dist-info/RECORD
pphp-3.3.1.dist-info/DESCRIPTION.rst
pphp-3.3.1.dist-info/METADATA
