Metadata-Version: 2.0
Name: pphp
Version: 3.3.1
Summary: A spinoff of PHP in Python
Home-page: https://kenny2github.github.io/pphp
Author: Ken Hilton
Author-email: kenny2minecraft@gmail.com
License: GNU GPLv3
Keywords: http php server
Platform: UNKNOWN
Classifier: Development Status :: 4 - Beta
Classifier: Intended Audience :: Developers
Classifier: Topic :: Internet :: WWW/HTTP :: HTTP Servers
Classifier: License :: OSI Approved :: GNU General Public License v3 (GPLv3)
Classifier: Programming Language :: Python :: 2.7
Classifier: Programming Language :: Python :: 3
Requires-Python: >=2.7
